Metadata-Version: 2.1
Name: example_package_fishball0741
Version: 0.0.1
Summary: Zombie Turn-based game
Project-URL: Homepage, https://github.com/pypa/sampleproject
Project-URL: Bug Tracker, https://github.com/pypa/sampleproject/issues
Author-email: Wing Man SIU <fishball0741@gmail.com>
License: Copyright (c) 2018 The Python Packaging Authority
License-File: LICENSE
Classifier: License :: OSI Approved :: MIT License
Classifier: Operating System :: OS Independent
Classifier: Programming Language :: Python :: 3
Requires-Python: >=3.7
